{
  "name": "Darrell Matthews",
  "age": 65,
  "address": {
    "street": "Mugu Key",
    "city": "Lazowpuv",
    "state": "AR",
    "zip": "07862"
  },
  "contact": {
    "phone": "(240) 754-8106",
    "servicePhone": "800215193"
  },
  "birthday": "1997-06-04T01:54:40.290Z",
  "ip": "238.25.46.144",
  "foo": "bar",
  "profile": {
    "about": "Obofutdo naw ivtid tom sodeb ribe kovvakfi bev viczir ime mucenzo hic oh watotwu mi teh ecersek. Garsisbu kuh bal tiwuku kas etefe suite vumluwi reh jotgu fodes racaluv tohsavuf fubuv wivezhu dusi fotokoh kedpofpot. Riul fos owpo janewhiv cavirar usdo cogtimo eho masahem jizverve ettudife sa ketgo huk ifu bone hako faco.",
    "bio": "Loccewjap ja givkisro be nawvu iw ru et dabo hej hucjerej si muzo zulan lojnoow wuzid. Ro wizisa keddomi rugluem go uwfa docuk opisdol koweru jojisiv ifofanfe agvini. Manakwi pilfampac se bu risdupam kujhiin gowsopge wadali vohimbu citeva jisu urduwci sivaamo nuobizol pes."
  },
  "apiKey": "6681257e15117da0cda952de060848c66fae3cac6415fd04fab8d2de054eaea8",
  "currency": {
    "code": "JPY",
    "name": "Japan Yen"
  }
}