{
  "name": "Nathaniel Reese",
  "age": 48,
  "address": {
    "street": "Lanit Turnpike",
    "city": "Nitkowop",
    "state": "IN",
    "zip": "54641"
  },
  "contact": {
    "phone": "(855) 254-5962",
    "servicePhone": "800957432"
  },
  "birthday": "1973-05-17T07:27:15.280Z",
  "ip": "105.248.25.155",
  "foo": "bar",
  "profile": {
    "about": "Ra tuzsig amobo numapni raz wedkah ofumoed bombibbud epub wihje zat deh ciede elratgi. Pi cewgizur benoz roran musisune tup ro jebewicu hupwo fuolrow iltanloc bec kegcutki amdip da. Koos wapdoz alaji fuozbi eji ek cubokjo hi pub doat ha zak vogomu. Zokurru dildo noj sodikipu dic girtedfu li vi rasof du ilfaafa hodaf rofmep.",
    "bio": "Ijo lekuwo zutiw apke nevde gi noleb la mab igavoera lobnib se dum joz. Fahtisluj mohcaru wo ekaredak uduvi hotu ik ilito wo filsekar naf kat ro ulsac vaki dedaz. Kuwako alki gebtot fuluor vi zecaksu cit gud bo fojovdac nad bapzi zip bulwiam di he johfees."
  },
  "apiKey": "b2a18e32b24472bdf7428ed5e2fda33ec03febf7e054cfce946481baab8cb868",
  "currency": {
    "code": "JPY",
    "name": "Japan Yen"
  }
}