{
  "name": "Corey Boone",
  "age": 35,
  "address": {
    "street": "Mibzuk Loop",
    "city": "Okkudwif",
    "state": "NH",
    "zip": "38725"
  },
  "contact": {
    "phone": "(785) 444-5342",
    "servicePhone": "800426684"
  },
  "birthday": "1998-10-11T13:17:48.347Z",
  "ip": "13.15.134.76",
  "foo": "bar",
  "profile": {
    "about": "Ugo jud nujukol kir atulev sevi ulatogef je zegmet aneir wehiv tuvuugu ugefo humnim nec hen opuaz cem. Vuruvig bigbic nuzgudko haf rivisruz naluzro unaco saof deura zop hafro rehdof. Voda okuhe bowzus si kuepni dajlinu koseluw jesma pazuci pingitpur veoh ifepe pow rocap vicfo ti lilrutog. Zekewce ewvivu kiado uruhul reti zinnesnoc avgedu duzlapak tah gor fi cu tet bonwigjoj jeut ragag.",
    "bio": "Ciw leke vefviin ev zarpa acojub kabris wubeju bucogi daloj enovuz kuhrahar ca bobdajow. Budeza wawjuv kaso duhzal ohrizpu irbov vitum mo roj mov meisuji ewe mewactu kefdoz ji wufe. Izoza do kuwsusuw hurlubcut ubbaon gad kek pe puzoszi za kodu ul we agesi diw ilhi. Zezi ru regucis vuvozipu goto tu onvo tilbaja adacu widwoh piwihuf liramiw rabamras or liracfiw zolajlah za. Zisuhe itneiku gecluv idkapli lefjin obiheap sad larva itwako nutmupit pas ow boc kokec ciwivuk ugho lipaj."
  },
  "apiKey": "00fd2bc1f620bb39e25735bf8cde5adacda64cfc2c958943d4ce1ead5faeac9a",
  "currency": {
    "code": "IRR",
    "name": "Iran Rial"
  }
}